{
	"era": "diesel",
	"name": "GTEL 3rd Generation 'Big Blow'",
	"works": "American Locomotive Company",
	"modeler": "Bossk",
	"model": "immersiverailroading:models/rolling_stock/locomotives/gtel_3rd_a/gtel_3rd_a.obj",
	"tex_variants": {
		"#1": "1",
		"#6": "6",
		"#7": "7",
		"#8": "8",
		"#17": "17",
		"#30": "30"
	},
	"properties": {
		"fuel_efficiency_%": 100,
		"fuel_capacity_l": 2400,
		"horsepower": 4250,
		"tractive_effort_lbf": 106156,
		"max_speed_kmh": 96,
		"weight_kg": 100000
	},
	"passenger": {
		"slots": 3,
		"center_x": 7.3125,
		"center_y": 2.375,
		"length": 0.9375,
		"width": 2.25
	},
	"trucks": {
		"front": 6.25,
		"rear": -6.25
	},
	"couplers": {
		"front_offset": -0.125,
		"rear_offset": -0.125
	}
}
